anycmd/__init__.py
anycmd/anycmd.py
anycmd_jupyter_magic-0.1.4.dist-info/licenses/LICENSE
anycmd_jupyter_magic-0.1.4.dist-info/METADATA
anycmd_jupyter_magic-0.1.4.dist-info/WHEEL
anycmd_jupyter_magic-0.1.4.dist-info/top_level.txt
anycmd_jupyter_magic-0.1.4.dist-info/RECORD
