Metadata-Version: 2.4
Name: anycmd-jupyter-magic
Version: 0.1.4
Summary: A versatile Jupyter cell magic that allows running a cell with any command line utility.
Home-page: https://github.com/zenarcher007/AnyCmd
Author: Justin Douty
Author-email: jdouty03@icloud.com
License: MIT
Keywords: ipython,jupyter,magic,cell magic,command
Platform: any
Classifier: Framework :: IPython
Classifier: Framework :: Jupyter
Classifier: Framework :: Jupyter :: JupyterLab
Classifier: Framework :: Jupyter :: JupyterLab :: Extensions
Classifier: Development Status :: 4 - Beta
Classifier: Intended Audience :: Developers
Classifier: Operating System :: OS Independent
Classifier: Programming Language :: Python
Classifier: Programming Language :: Python :: 3.7
License-File: LICENSE
Requires-Dist: argparse
Requires-Dist: uuid
Dynamic: author
Dynamic: author-email
Dynamic: classifier
Dynamic: description
Dynamic: description-content-type
Dynamic: home-page
Dynamic: keywords
Dynamic: license
Dynamic: license-file
Dynamic: platform
Dynamic: requires-dist
Dynamic: summary
